README.md
setup.cfg
setup.py
s3po/__init__.py
s3po/batch.py
s3po/connection.py
s3po/exceptions.py
s3po/util.py
s3po.egg-info/PKG-INFO
s3po.egg-info/SOURCES.txt
s3po.egg-info/dependency_links.txt
s3po.egg-info/requires.txt
s3po.egg-info/top_level.txt
s3po/backends/__init__.py
s3po/backends/memory.py
s3po/backends/s3.py
s3po/backends/swift.py
test/test_batch.py
test/test_connection.py
test/test_util.py