Metadata-Version: 1.1
Name: s3po
Version: 0.5.0
Summary: An uploading daemon for S3
Home-page: http://github.com/seomoz/s3po
Author: Dan Lecocq
Author-email: dan@moz.com
License: MIT
Platform: Posix; MacOS X
Classifier: License :: OSI Approved :: MIT License
Classifier: Development Status :: 3 - Alpha
Classifier: Environment :: Web Environment
Classifier: Intended Audience :: Developers
Classifier: Topic :: Internet :: WWW/HTTP
